debutizer/__init__.py
debutizer/__main__.py
debutizer/_license_full_text.py
debutizer/_list_backed_container.py
debutizer/binary_paragraph.py
debutizer/changelog.py
debutizer/compat.py
debutizer/conffiles.py
debutizer/control.py
debutizer/copyright.py
debutizer/deb822_schema.py
debutizer/deb822_utils.py
debutizer/environment.py
debutizer/errors.py
debutizer/package_py.py
debutizer/print_utils.py
debutizer/registry.py
debutizer/relation.py
debutizer/source_package.py
debutizer/source_paragraph.py
debutizer/subprocess_utils.py
debutizer/version.py
debutizer/commands/__init__.py
debutizer/commands/artifacts.py
debutizer/commands/build.py
debutizer/commands/check.py
debutizer/commands/command.py
debutizer/commands/config_file.py
debutizer/commands/env_argparse.py
debutizer/commands/local_repo.py
debutizer/commands/root.py
debutizer/commands/source.py
debutizer/commands/upload.py
debutizer/commands/utils.py
debutizer/commands/version.py
debutizer/commands/pbuilder_hooks/C10shell
debutizer/commands/pbuilder_hooks/D70results
debutizer/commands/repo_metadata/__init__.py
debutizer/commands/repo_metadata/packages.py
debutizer/commands/repo_metadata/release.py
debutizer/commands/repo_metadata/sources.py
debutizer/commands/repo_metadata/utils.py
debutizer/commands/upload_targets/__init__.py
debutizer/commands/upload_targets/abstract.py
debutizer/commands/upload_targets/ppa.py
debutizer/commands/upload_targets/s3.py
debutizer/upstreams/__init__.py
debutizer/upstreams/base.py
debutizer/upstreams/git.py
debutizer/upstreams/local.py
debutizer/upstreams/null.py
debutizer/upstreams/source_package.py
debutizer-0.14.0.dist-info/LICENSE
debutizer-0.14.0.dist-info/LICENSE.spdx
debutizer-0.14.0.dist-info/METADATA
debutizer-0.14.0.dist-info/WHEEL
debutizer-0.14.0.dist-info/entry_points.txt
debutizer-0.14.0.dist-info/top_level.txt
debutizer-0.14.0.dist-info/RECORD
