Metadata-Version: 2.1
Name: debutizer
Version: 0.14.0
Summary: A tool for managing APT packages
Home-page: https://github.com/velovix/debutizer
Author: Tyler Compton
Author-email: xaviosx@gmail.com
Keywords: deb,apt
Classifier: Development Status :: 3 - Alpha
Classifier: Intended Audience :: Developers
Classifier: Topic :: Software Development :: Build Tools
Classifier: License :: OSI Approved :: BSD License
Classifier: Programming Language :: Python :: 3
Classifier: Programming Language :: Python :: 3 :: Only
Requires-Python: >=3.6, <4
License-File: LICENSE
License-File: LICENSE.spdx
Requires-Dist: python-debian
Requires-Dist: pyxdg
Requires-Dist: requests
Requires-Dist: flask
Requires-Dist: PyYAML
Provides-Extra: dev
Requires-Dist: pre-commit ~=2.15 ; extra == 'dev'
Requires-Dist: pytest ~=6.2 ; extra == 'dev'
Requires-Dist: black ==21.9b0 ; extra == 'dev'
Requires-Dist: isort ~=5.9 ; extra == 'dev'
Requires-Dist: mypy ~=0.910 ; extra == 'dev'
Requires-Dist: types-requests ; extra == 'dev'
Requires-Dist: build ; extra == 'dev'
Requires-Dist: types-setuptools ; extra == 'dev'
Requires-Dist: sphinx ; extra == 'dev'
Requires-Dist: furo ; extra == 'dev'
